composabl/core.cpython-311-darwin.so
composabl/__init__.cpython-311-darwin.so
composabl/ray.cpython-311-darwin.so
composabl-0.19.1.dist-info/RECORD
composabl-0.19.1.dist-info/WHEEL
composabl-0.19.1.dist-info/entry_points.txt
composabl-0.19.1.dist-info/top_level.txt
composabl-0.19.1.dist-info/METADATA
